aiohttp_sse_client/__init__.py
aiohttp_sse_client/client.py
aiohttp_sse_client-0.2.1.dist-info/AUTHORS.rst
aiohttp_sse_client-0.2.1.dist-info/LICENSE
aiohttp_sse_client-0.2.1.dist-info/METADATA
aiohttp_sse_client-0.2.1.dist-info/WHEEL
aiohttp_sse_client-0.2.1.dist-info/top_level.txt
aiohttp_sse_client-0.2.1.dist-info/RECORD
