Metadata-Version: 1.1
Name: aiohttp-sse-client
Version: 0.2.1
Summary: A Server-Sent Event python client base on aiohttp
Home-page: https://github.com/rtfol/aiohttp-sse-client
Author: Jason Hu
Author-email: awaregit@gmail.com
License: Apache License 2.0
Keywords: aiohttp_sse_client
Platform: UNKNOWN
Classifier: Development Status :: 2 - Pre-Alpha
Classifier: Intended Audience :: Developers
Classifier: License :: OSI Approved :: Apache Software License
Classifier: Natural Language :: English
Classifier: Programming Language :: Python :: 3
Classifier: Programming Language :: Python :: 3.6
Classifier: Programming Language :: Python :: 3.7
Classifier: Programming Language :: Python :: 3.8
